{"numero":"263","rotulo":"Art. 263","situacao":"vigente","rubricas":[],"dispositivos":[{"tipo":"caput","situacao":"vigente","texto":"O Decreto-Lei n.º 2.848, de 7 de dezembro de 1940 (Código Penal), passa a vigorar com as seguintes alterações:","notas":[],"ancoras":["c263","art263"]},{"tipo":"citacao","situacao":"vigente","texto":"1) Art. 121 ............................................................","notas":[]},{"tipo":"citacao","situacao":"vigente","texto":"§ 4º No homicídio culposo, a pena é aumentada de um terço, se o crime resulta de inobservância de regra técnica de profissão, arte ou ofício, ou se o agente deixa de prestar imediato socorro à vítima, não procura diminuir as conseqüências do seu ato, ou foge para evitar prisão em flagrante. Sendo doloso o homicídio, a pena é aumentada de um terço, se o crime é praticado contra pessoa menor de catorze anos.","notas":[]},{"tipo":"citacao","situacao":"vigente","texto":"2) Art. 129 ...............................................................","notas":[]},{"tipo":"citacao","situacao":"vigente","texto":"§ 7º Aumenta-se a pena de um terço, se ocorrer qualquer das hipóteses do art. 121, § 4º.","notas":[]},{"tipo":"citacao","situacao":"vigente","texto":"§ 8º Aplica-se à lesão culposa o disposto no § 5º do art. 121.","notas":[]},{"tipo":"citacao","situacao":"vigente","texto":"3) Art. 136.................................................................","notas":[]},{"tipo":"citacao","situacao":"vigente","texto":"§ 3º Aumenta-se a pena de um terço, se o crime é praticado contra pessoa menor de catorze anos.","notas":[]},{"tipo":"citacao","situacao":"vigente","texto":"4) Art. 213 ..................................................................","notas":[]},{"tipo":"citacao","situacao":"vigente","texto":"Parágrafo único. Se a ofendida é menor de catorze anos:","notas":[]},{"tipo":"citacao","situacao":"vigente","texto":"Pena - reclusão de quatro a dez anos.","notas":[]},{"tipo":"citacao","situacao":"vigente","texto":"5) Art. 214...................................................................","notas":[]},{"tipo":"citacao","situacao":"vigente","texto":"Parágrafo único. Se o ofendido é menor de catorze anos:","notas":[]},{"tipo":"citacao","situacao":"vigente","texto":"Pena - reclusão de três a nove anos.»","notas":[]}],"hierarquia":{"parte":{"rotulo":"Disposições Finais e Transitórias","nome":null,"notas":[]}},"texto":"Art. 263 O Decreto-Lei n.º 2.848, de 7 de dezembro de 1940 (Código Penal), passa a vigorar com as seguintes alterações:\n1) Art. 121 ............................................................\n§ 4º No homicídio culposo, a pena é aumentada de um terço, se o crime resulta de inobservância de regra técnica de profissão, arte ou ofício, ou se o agente deixa de prestar imediato socorro à vítima, não procura diminuir as conseqüências do seu ato, ou foge para evitar prisão em flagrante. Sendo doloso o homicídio, a pena é aumentada de um terço, se o crime é praticado contra pessoa menor de catorze anos.\n2) Art. 129 ...............................................................\n§ 7º Aumenta-se a pena de um terço, se ocorrer qualquer das hipóteses do art. 121, § 4º.\n§ 8º Aplica-se à lesão culposa o disposto no § 5º do art. 121.\n3) Art. 136.................................................................\n§ 3º Aumenta-se a pena de um terço, se o crime é praticado contra pessoa menor de catorze anos.\n4) Art. 213 ..................................................................\nParágrafo único. Se a ofendida é menor de catorze anos:\nPena - reclusão de quatro a dez anos.\n5) Art. 214...................................................................\nParágrafo único. Se o ofendido é menor de catorze anos:\nPena - reclusão de três a nove anos.»","textoHistorico":"","caput":"O Decreto-Lei n.º 2.848, de 7 de dezembro de 1940 (Código Penal), passa a vigorar com as seguintes alterações:"}