{"numero":"365","rotulo":"Art. 365","situacao":"vigente","dispositivos":[{"tipo":"rubrica","situacao":"vigente","texto":"Fuga em presença do inimigo","notas":[]},{"tipo":"caput","situacao":"vigente","texto":"Fugir o militar, ou incitar à fuga, em presença do inimigo:","notas":[],"ancoras":["c365","art365"]},{"tipo":"pena","situacao":"vigente","texto":"Pena - morte, grau máximo; reclusão, de vinte anos, grau mínimo.","notas":[],"ancoras":[]}],"hierarquia":{"parte":{"rotulo":"PARTE ESPECIAL","nome":null,"notas":[]},"livro":{"rotulo":"LIVRO II","nome":"DOS CRIMES MILITARES EM TEMPO","notas":[]},"titulo":{"rotulo":"TÍTULO I","nome":"DO FAVORECIMENTO AO INIMIGO","notas":[]},"capitulo":{"rotulo":"CAPÍTULO III","nome":"DA COBARDIA","notas":[]}},"texto":"Fuga em presença do inimigo\nArt. 365 Fugir o militar, ou incitar à fuga, em presença do inimigo:\nPena - morte, grau máximo; reclusão, de vinte anos, grau mínimo.","textoHistorico":"","rubricas":["Fuga em presença do inimigo"],"caput":"Fugir o militar, ou incitar à fuga, em presença do inimigo:","palavrasChave":[]}