{"numero":"381","rotulo":"Art. 381","situacao":"vigente","rubricas":["Tolerância culposa"],"dispositivos":[{"tipo":"rubrica","situacao":"vigente","texto":"Tolerância culposa","notas":[]},{"tipo":"caput","situacao":"vigente","texto":"Deixar, por culpa, evadir-se prisioneiro:","notas":[],"ancoras":["c381","art381"]},{"tipo":"pena","situacao":"vigente","texto":"Pena - reclusão, até quatro anos.","notas":[],"ancoras":[]}],"hierarquia":{"parte":{"rotulo":"PARTE ESPECIAL","nome":null,"notas":[]},"livro":{"rotulo":"LIVRO II","nome":"DOS CRIMES MILITARES EM TEMPO","notas":[]},"titulo":{"rotulo":"TÍTULO I","nome":"DO FAVORECIMENTO AO INIMIGO","notas":[]},"capitulo":{"rotulo":"CAPÍTULO VII","nome":"DA INOBSERVÂNCIA DO DEVER MILITAR","notas":[]}},"texto":"Tolerância culposa\nArt. 381 Deixar, por culpa, evadir-se prisioneiro:\nPena - reclusão, até quatro anos.","textoHistorico":"","caput":"Deixar, por culpa, evadir-se prisioneiro:"}