{"numero":"448","rotulo":"Art. 448","situacao":"vigente","rubricas":["Lavratura de ata","Anexação de cópia da ata"],"dispositivos":[{"tipo":"rubrica","situacao":"vigente","texto":"Lavratura de ata","notas":[]},{"tipo":"caput","situacao":"vigente","texto":"O escrivão lavrará ata circunstanciada de tôdas as ocorrências na sessão de julgamento.","notas":[],"ancoras":["c448","art448"]},{"tipo":"rubrica","situacao":"vigente","texto":"Anexação de cópia da ata","notas":[]},{"tipo":"paragrafo","situacao":"vigente","texto":"Parágrafo único. Da ata será anexada aos autos cópia autêntica datilografada e rubricada pelo escrivão.","notas":[],"ancoras":["art448p"]}],"hierarquia":{"parte":{"rotulo":"DISPOSIÇÕES GERAIS","nome":null,"notas":[]},"livro":{"rotulo":"LIVRO II","nome":null,"notas":[]},"titulo":{"rotulo":"TÍTULO I","nome":"DO PROCESSO ORDINÁRIO","notas":[]},"capitulo":{"rotulo":"CAPíTULO úNICO","nome":"DA INSTRUÇÃO CRIMINAL","notas":[]},"secao":{"rotulo":"SEÇÃO VII","nome":null,"notas":[]}},"texto":"Lavratura de ata\nArt. 448 O escrivão lavrará ata circunstanciada de tôdas as ocorrências na sessão de julgamento.\nAnexação de cópia da ata\nParágrafo único. Da ata será anexada aos autos cópia autêntica datilografada e rubricada pelo escrivão.","textoHistorico":"","caput":"O escrivão lavrará ata circunstanciada de tôdas as ocorrências na sessão de julgamento."}