{"numero":"211","rotulo":"Art. 211","situacao":"vigente","rubricas":["Destruição, subtração ou ocultação de cadáver"],"dispositivos":[{"tipo":"rubrica","situacao":"vigente","texto":"Destruição, subtração ou ocultação de cadáver","notas":[]},{"tipo":"caput","situacao":"vigente","texto":"Destruir, subtrair ou ocultar cadáver ou parte dele:","notas":[],"ancoras":["c211","art211"],"links":[]},{"tipo":"pena","situacao":"vigente","texto":"Pena - reclusão, de um a três anos, e multa.","notas":[],"ancoras":[]}],"hierarquia":{"parte":{"rotulo":"PARTE ESPECIAL","nome":null,"notas":["(Vide Lei nº 7.209, de 1984)"]},"titulo":{"rotulo":"TÍTULO V","nome":"DOS CRIMES CONTRA O SENTIMENTO RELIGIOSO E CONTRA O RESPEITO AOS MORTOS","notas":[]},"capitulo":{"rotulo":"CAPÍTULO II","nome":"DOS CRIMES CONTRA O RESPEITO AOS MORTOS","notas":[]}},"texto":"Destruição, subtração ou ocultação de cadáver\nArt. 211 Destruir, subtrair ou ocultar cadáver ou parte dele:\nPena - reclusão, de um a três anos, e multa.","textoHistorico":"","caput":"Destruir, subtrair ou ocultar cadáver ou parte dele:"}