{"numero":"61","rotulo":"Art. 61","situacao":"vigente","dispositivos":[{"tipo":"caput","situacao":"vigente","texto":"O autuado terá prazo de 10 (dez) dias para a apresentação da defesa, contado da data da intimação, que será feita:","notas":[],"ancoras":["art61"]},{"tipo":"texto","situacao":"vigente","texto":"I  pelo autuante, no instrumento de autuação, quando for lavrado na presença do infrator;","notas":[],"ancoras":[]},{"tipo":"texto","situacao":"vigente","texto":"II  por via postal, com aviso de recebimento.","notas":[],"ancoras":[]}],"hierarquia":{"titulo":{"rotulo":"TÍTULO IV","nome":"Da Política de Atendimento ao Idoso","notas":[]},"capitulo":{"rotulo":"CAPÍTULO IV","nome":"Das Infrações Administrativas","notas":[]}},"texto":"Art. 61 O autuado terá prazo de 10 (dez) dias para a apresentação da defesa, contado da data da intimação, que será feita:\nI  pelo autuante, no instrumento de autuação, quando for lavrado na presença do infrator;\nII  por via postal, com aviso de recebimento.","textoHistorico":"","rubricas":[],"caput":"O autuado terá prazo de 10 (dez) dias para a apresentação da defesa, contado da data da intimação, que será feita:","palavrasChave":[]}