{"numero":"24","rotulo":"Art. 24","situacao":"vigente","dispositivos":[{"tipo":"rubrica","situacao":"vigente","texto":"Instrumento de emprego usual na prática de furto","notas":[]},{"tipo":"caput","situacao":"vigente","texto":"Fabricar, ceder ou vender gazua ou instrumento empregado usualmente na prática de crime de furto:","notas":[],"ancoras":["art24"]},{"tipo":"texto","situacao":"vigente","texto":"Pena  prisão simples, de seis meses a dois anos, e multa, de trezentos mil réis a três contos de réis.","notas":[],"ancoras":[]}],"hierarquia":{"parte":{"rotulo":"PARTE ESPECIAL","nome":null,"notas":[]},"capitulo":{"rotulo":"CAPÍTULO I","nome":"DAS CONTRAVENÇÕES REFERENTES À PESSOA","notas":[]}},"texto":"Instrumento de emprego usual na prática de furto\nArt. 24 Fabricar, ceder ou vender gazua ou instrumento empregado usualmente na prática de crime de furto:\nPena  prisão simples, de seis meses a dois anos, e multa, de trezentos mil réis a três contos de réis.","textoHistorico":"","rubricas":["Instrumento de emprego usual na prática de furto"],"caput":"Fabricar, ceder ou vender gazua ou instrumento empregado usualmente na prática de crime de furto:","palavrasChave":[]}