{"numero":"183","rotulo":"Art. 183","situacao":"vigente","dispositivos":[{"tipo":"caput","situacao":"vigente","texto":"Parar o veículo sobre a faixa de pedestres na mudança de sinal luminoso:","notas":[],"ancoras":["c183","art183"]},{"tipo":"infracao","situacao":"vigente","texto":"Infração - média;","notas":[],"ancoras":[]},{"tipo":"penalidade","situacao":"vigente","texto":"Penalidade - multa.","notas":[],"ancoras":[]}],"hierarquia":{"capitulo":{"rotulo":"CAPÍTULO XV","nome":"DAS INFRAÇÕES","notas":[]}},"texto":"Art. 183 Parar o veículo sobre a faixa de pedestres na mudança de sinal luminoso:\nInfração - média;\nPenalidade - multa.","textoHistorico":"","rubricas":[],"caput":"Parar o veículo sobre a faixa de pedestres na mudança de sinal luminoso:","palavrasChave":[]}