{"numero":"276","rotulo":"Art. 276","situacao":"vigente","rubricas":[],"dispositivos":[{"tipo":"caput","situacao":"vigente","texto":"As partes não intervirão na nomeação do perito.","notas":[],"ancoras":["c276","art276"]}],"hierarquia":{"parte":{"rotulo":"DISPOSIÇÕES GERAIS","nome":null,"notas":[]},"titulo":{"rotulo":"TÍTULO VIII","nome":"DO JUIZ, DO MINISTÉRIO PÚBLICO, DO ACUSADO E DEFENSOR,","notas":[]},"capitulo":{"rotulo":"CAPÍTULO VI","nome":"DOS PERITOS E INTÉRPRETES","notas":[]}},"texto":"Art. 276 As partes não intervirão na nomeação do perito.","textoHistorico":"","caput":"As partes não intervirão na nomeação do perito."}