{"numero":"517","rotulo":"Art. 517","situacao":"vigente","rubricas":[],"dispositivos":[{"tipo":"caput","situacao":"vigente","texto":"Recebida a denúncia ou a queixa, será o acusado citado, na forma estabelecida no Capítulo I do Título X do Livro I.","notas":[],"ancoras":["c517","art517"]}],"hierarquia":{"parte":{"rotulo":"DISPOSIÇÕES GERAIS","nome":null,"notas":[]},"livro":{"rotulo":"LIVRO II","nome":"DOS PROCESSOS EM ESPÉCIE","notas":[]},"titulo":{"rotulo":"TÍTULO II","nome":"DOS PROCESSOS ESPECIAIS","notas":[]},"capitulo":{"rotulo":"CAPÍTULO II","nome":"DO PROCESSO E DO JULGAMENTO DOS CRIMES","notas":[]}},"texto":"Art. 517 Recebida a denúncia ou a queixa, será o acusado citado, na forma estabelecida no Capítulo I do Título X do Livro I.","textoHistorico":"","caput":"Recebida a denúncia ou a queixa, será o acusado citado, na forma estabelecida no Capítulo I do Título X do Livro I."}